rediz/__init__.py
rediz/admin_client.py
rediz/client.py
rediz/conventions.py
rediz/rediz_test_config.py
rediz/samplers.py
rediz/utilities.py
rediz-1.0.12.dist-info/METADATA
rediz-1.0.12.dist-info/WHEEL
rediz-1.0.12.dist-info/entry_points.txt
rediz-1.0.12.dist-info/top_level.txt
rediz-1.0.12.dist-info/RECORD
