Metadata-Version: 2.1
Name: rediz
Version: 1.0.12
Summary: Powering community nowcasts at www.microprediction.org
Home-page: https://github.com/microprediction/rediz
Author: microprediction
Author-email: pcotton@intechinvestments.com
License: MIT
Platform: UNKNOWN
Classifier: License :: OSI Approved :: MIT License
Classifier: Programming Language :: Python :: 3
Classifier: Programming Language :: Python :: 3.9
Requires-Dist: microconventions (>=0.5.3)
Requires-Dist: fakeredis
Requires-Dist: getjson
Requires-Dist: redis
Requires-Dist: sortedcontainers
Requires-Dist: numpy
Requires-Dist: pymorton
Requires-Dist: scipy
